IDE2.py
PanchIDE-0.1.0.dist-info/METADATA
PanchIDE-0.1.0.dist-info/WHEEL
PanchIDE-0.1.0.dist-info/top_level.txt
PanchIDE-0.1.0.dist-info/RECORD
